composite_ufjc_scission_fenics_ufl/__init__.py
composite_ufjc_scission_fenics_ufl/characterizer.py
composite_ufjc_scission_fenics_ufl/composite_ufjc.py
composite_ufjc_scission_fenics_ufl/core.py
composite_ufjc_scission_fenics_ufl/default_parameters.py
composite_ufjc_scission_fenics_ufl/rate_dependence_scission.py
composite_ufjc_scission_fenics_ufl/scission_model.py
composite_ufjc_scission_fenics_ufl/utility.py
composite_ufjc_scission_fenics_ufl-1.3.7.dist-info/LICENSE
composite_ufjc_scission_fenics_ufl-1.3.7.dist-info/METADATA
composite_ufjc_scission_fenics_ufl-1.3.7.dist-info/WHEEL
composite_ufjc_scission_fenics_ufl-1.3.7.dist-info/top_level.txt
composite_ufjc_scission_fenics_ufl-1.3.7.dist-info/RECORD
